Metadata-Version: 2.1
Name: serdeserb
Version: 0.0
Summary: don't use it, even if you have to
Author-email: kirkat6@gmail.com
